setup.py
pyS3fs/__init__.py
pyS3fs/config.py
pyS3fs.egg-info/PKG-INFO
pyS3fs.egg-info/SOURCES.txt
pyS3fs.egg-info/dependency_links.txt
pyS3fs.egg-info/requires.txt
pyS3fs.egg-info/top_level.txt
pyS3fs/fs/S3fs.py
pyS3fs/fs/__init__.py
pyS3fs/fs/cache.py
pyS3fs/fs/node.py
pyS3fs/fs/node_utils.py
pyS3fs/net/S3.py
pyS3fs/net/__init__.py
scripts/pyS3fs