Metadata-Version: 1.0
Name: pyS3fs
Version: 0.2
Summary: Mount Amazon's S3 bucket as a filesystem
Home-page: http://github.com/rbaron/pyS3fs
Author: UNKNOWN
Author-email: UNKNOWN
License: UNKNOWN
Platform: UNKNOWN
